stegoprng/__init__.py
stegoprng/stego.py
stegoprng/helpers/__init__.py
stegoprng/helpers/encryption.py
stegoprng/helpers/file_handler.py
stegoprng/helpers/steganography.py
stegoprng-1.0.1.dist-info/METADATA
stegoprng-1.0.1.dist-info/RECORD
stegoprng-1.0.1.dist-info/WHEEL
stegoprng-1.0.1.dist-info/top_level.txt
